{
  "name": "EMILY RODRIGUEZ",
  "contact": {
    "location": "Mountain View, CA 94043",
    "phone": "(650) 123-4567",
    "email": "emily.rodriguez@example.com",
    "linkedin": "linkedin.com/in/emilyrodriguez"
  },
  "education": [
    {
      "institution": "MASSACHUSETTS INSTITUTE OF TECHNOLOGY (MIT)",
      "degree": "Master of Science in Computer Science - Artificial Intelligence",
      "graduation_date": "December 2023",
      "gpa": "3.94/4.0",
      "relevant_coursework": []
    },
    {
      "institution": "UNIVERSITY OF ILLINOIS URBANA-CHAMPAIGN",
      "degree": "Bachelor of Science in Statistics with Computer Science minor",
      "graduation_date": "May 2021",
      "gpa": "3.88/4.0",
      "relevant_coursework": []
    }
  ],
  "experience": [
    {
      "position": "Machine Learning Engineer",
      "company": "NVIDIA",
      "location": "Santa Clara, CA",
      "duration": "January 2024 - Present",
      "responsibilities": [
        "Develop and optimize deep learning models for computer vision applications",
        "Implement CUDA optimizations that improved training speed by 35%",
        "Collaborate with research team on next-generation AI architectures",
        "Created automated CI/CD pipeline for model deployment using Kubernetes"
      ]
    },
    {
      "position": "Data Science Intern",
      "company": "APPLE",
      "location": "Cupertino, CA",
      "duration": "June 2022 - December 2023",
      "responsibilities": [
        "Designed recommendation algorithms for Apple Music that increased user engagement by 12%",
        "Built data pipelines processing over 15TB of daily user interaction data",
        "Created visualization dashboards for executive reporting using Tableau",
        "Implemented A/B testing framework for feature evaluation"
      ]
    },
    {
      "position": "Software Engineering Intern",
      "company": "AMAZON",
      "location": "Seattle, WA",
      "duration": "May 2021 - August 2021",
      "responsibilities": [
        "Built microservices for inventory management system using Java and AWS",
        "Developed REST APIs handling over 5,000 requests per minute",
        "Optimized database queries reducing latency by 27%",
        "Participated in agile development process and code reviews"
      ]
    }
  ],
  "projects": [
    {
      "name": "MULTIMODAL HEALTHCARE DIAGNOSTICS SYSTEM",
      "description": "Developed an AI system that analyzes medical images, patient history, and lab results",
      "technologies": [
        "PyTorch",
        "Federated learning"
      ]
    },
    {
      "name": "EXPLAINABLE AI FRAMEWORK",
      "description": "Created a framework for generating human-understandable explanations for complex ML models",
      "technologies": [
        "LIME",
        "SHAP",
        "custom attribution methods"
      ]
    },
    {
      "name": "SMART CITY TRAFFIC OPTIMIZATION",
      "description": "Built traffic flow prediction system using spatio-temporal graph neural networks",
      "technologies": [
        "TensorFlow",
        "Graph neural networks",
        "Edge devices"
      ]
    }
  ],
  "skills": {
    "languages": [
      "Python",
      "R",
      "SQL",
      "Julia",
      "Java",
      "C++",
      "JavaScript"
    ],
    "tools": [
      "PyTorch",
      "TensorFlow",
      "scikit-learn",
      "Pandas",
      "NumPy",
      "Hugging Face",
      "AWS",
      "Google Cloud",
      "Hadoop",
      "Spark",
      "Kafka",
      "Airflow",
      "Tableau",
      "PowerBI",
      "Matplotlib",
      "D3.js",
      "Plotly",
      "Git",
      "Docker",
      "Kubernetes",
      "Linux",
      "Jupyter",
      "VS Code"
    ]
  }
}